app.py
dbgr/__init__.py
dbgr/arguments.py
dbgr/commands.py
dbgr/completion.py
dbgr/environment.py
dbgr/meta.py
dbgr/reporting.py
dbgr/requests.py
dbgr/results.py
dbgr/session.py
dbgr/tools.py
dbgr/types.py
tests/__init__.py
tests/arguments.py
tests/commands.py
tests/completion.py
tests/conftest.py
tests/environment.py
tests/meta.py
tests/reporting.py
tests/requests.py
tests/results.py
tests/session.py
tests/tools.py
tests/types.py
dbgr-1.3.0.dist-info/LICENCE
dbgr-1.3.0.dist-info/METADATA
dbgr-1.3.0.dist-info/WHEEL
dbgr-1.3.0.dist-info/entry_points.txt
dbgr-1.3.0.dist-info/top_level.txt
dbgr-1.3.0.dist-info/RECORD
