Metadata-Version: 2.1
Name: dbgr
Version: 1.3.0
Summary: REST API testing tool
Home-page: https://github.com/JakubTesarek/dbgr
Author: Jakub Tesárek
Author-email: jakub@tesarek.me
License: APACHE LICENSE 2.0
Keywords: api rest api testing
Platform: UNKNOWN
Classifier: Development Status :: 4 - Beta
Classifier: License :: OSI Approved :: Apache Software License
Classifier: Intended Audience :: Developers
Requires-Python: >=3.6
Requires-Dist: aiohttp
Requires-Dist: colorama
Requires-Dist: argcomplete
Requires-Dist: pygments
Requires-Dist: dateparser
Provides-Extra: test
Requires-Dist: twine ; extra == 'test'
Requires-Dist: pytest ; extra == 'test'
Requires-Dist: pylint ; extra == 'test'
Requires-Dist: pytest-cov ; extra == 'test'
Requires-Dist: pytest-asyncio ; extra == 'test'
Requires-Dist: codecov ; extra == 'test'
Requires-Dist: sphinx ; extra == 'test'
Requires-Dist: sphinxcontrib-spelling ; extra == 'test'
